twindtk/config.py
twindtk/main.py
twindtk/cls/__init__.py
twindtk/cls/tw.py
twindtk/twt/__init__.py
twindtk/twt/btn.py
twindtk/twt/button.py
twindtk/twt/input.py
twindtk/twt/label.py
twindtk-0.2.dist-info/METADATA
twindtk-0.2.dist-info/WHEEL
twindtk-0.2.dist-info/top_level.txt
twindtk-0.2.dist-info/RECORD
