Metadata-Version: 2.1
Name: twindtk
Version: 0.2
Requires-Dist: ttkbootstrap
